orsim/__init__.py
orsim/celery_config.py
orsim/worker.py
orsim/core/__init__.py
orsim/core/orsim_agent.py
orsim/core/orsim_env.py
orsim/core/orsim_scheduler.py
orsim/messenger/__init__.py
orsim/messenger/messenger.py
orsim/tasks/__init__.py
orsim/tasks/agent_task.py
orsim/utils/__init__.py
orsim/utils/utils.py
tests/__init__.py
tests/test_orsim.py
orsim-0.3.3.dist-info/AUTHORS.rst
orsim-0.3.3.dist-info/LICENSE
orsim-0.3.3.dist-info/METADATA
orsim-0.3.3.dist-info/WHEEL
orsim-0.3.3.dist-info/top_level.txt
orsim-0.3.3.dist-info/RECORD
