Metadata-Version: 2.1
Name: orsim
Version: 0.3.3
Summary: Distributed Agent based Simulation Library
Home-page: https://github.com/IORA-NUS/orsim
Author: iora_dev_team
License: MIT
Platform: UNKNOWN
Classifier: Development Status :: 2 - Pre-Alpha
Classifier: Intended Audience :: Science/Research
Classifier: Intended Audience :: Developers
Classifier: License :: OSI Approved :: MIT License
Classifier: Natural Language :: English
Classifier: Programming Language :: Python :: 3
Classifier: Programming Language :: Python :: 3.8
License-File: LICENSE
License-File: AUTHORS.rst
